mekaconverter/__converter__.py
mekaconverter/__init__.py
mekaconverter/__mekaconverter__.py
mekaconverter-1.1.0.dist-info/METADATA
mekaconverter-1.1.0.dist-info/WHEEL
mekaconverter-1.1.0.dist-info/dependency_links.txt
mekaconverter-1.1.0.dist-info/entry_points.txt
mekaconverter-1.1.0.dist-info/top_level.txt
mekaconverter-1.1.0.dist-info/RECORD
