Metadata-Version: 2.1
Name: mekaconverter
Version: 1.1.0
Summary: A tool to convert Meka's assets to JSON format.
Home-page: https://github.com/TheMekaverse/MekaConverter
Author: Thibault Walterspieler
License: MIT
Platform: UNKNOWN
Requires-Python: >=3.9
Requires-Dist: black (==22.1.0)
Requires-Dist: click (==8.0.4)
Requires-Dist: mypy-extensions (==0.4.3)
Requires-Dist: pathspec (==0.9.0)
Requires-Dist: platformdirs (==2.5.1)
Requires-Dist: pyfiglet (==0.8.post1)
Requires-Dist: toml (==0.10.2)
Requires-Dist: tomli (==2.0.1)
Requires-Dist: typing-extensions (==4.1.1)
Requires-Dist: zipp (==3.7.0)
